{
  "greet": {
    "precision": 1.0,
    "recall": 1.0,
    "f1-score": 1.0,
    "support": 12,
    "confused_with": {}
  },
  "ask_physical_activity": {
    "precision": 1.0,
    "recall": 1.0,
    "f1-score": 1.0,
    "support": 9,
    "confused_with": {}
  },
  "ask_deep_breathing": {
    "precision": 1.0,
    "recall": 1.0,
    "f1-score": 1.0,
    "support": 3,
    "confused_with": {}
  },
  "ask_chair_position": {
    "precision": 1.0,
    "recall": 1.0,
    "f1-score": 1.0,
    "support": 10,
    "confused_with": {}
  },
  "ask_shoulder_stretches": {
    "precision": 1.0,
    "recall": 1.0,
    "f1-score": 1.0,
    "support": 8,
    "confused_with": {}
  },
  "ask_pushup_exercise": {
    "precision": 1.0,
    "recall": 1.0,
    "f1-score": 1.0,
    "support": 8,
    "confused_with": {}
  },
  "ask_neck_stretches": {
    "precision": 1.0,
    "recall": 1.0,
    "f1-score": 1.0,
    "support": 7,
    "confused_with": {}
  },
  "ask_seated_side_bends_exercise": {
    "precision": 1.0,
    "recall": 1.0,
    "f1-score": 1.0,
    "support": 8,
    "confused_with": {}
  },
  "ask_chair_squats_exercise": {
    "precision": 1.0,
    "recall": 1.0,
    "f1-score": 1.0,
    "support": 7,
    "confused_with": {}
  },
  "goodbye": {
    "precision": 1.0,
    "recall": 1.0,
    "f1-score": 1.0,
    "support": 10,
    "confused_with": {}
  },
  "out_of_scope": {
    "precision": 1.0,
    "recall": 1.0,
    "f1-score": 1.0,
    "support": 16,
    "confused_with": {}
  },
  "ask_upper_back_stretches": {
    "precision": 1.0,
    "recall": 1.0,
    "f1-score": 1.0,
    "support": 8,
    "confused_with": {}
  },
  "affirm": {
    "precision": 1.0,
    "recall": 1.0,
    "f1-score": 1.0,
    "support": 18,
    "confused_with": {}
  },
  "ask_seated_leg_extensions_exercise": {
    "precision": 1.0,
    "recall": 1.0,
    "f1-score": 1.0,
    "support": 8,
    "confused_with": {}
  },
  "deny": {
    "precision": 1.0,
    "recall": 1.0,
    "f1-score": 1.0,
    "support": 14,
    "confused_with": {}
  },
  "ask_wrist_exercise": {
    "precision": 1.0,
    "recall": 1.0,
    "f1-score": 1.0,
    "support": 8,
    "confused_with": {}
  },
  "ask_chest_stretches": {
    "precision": 1.0,
    "recall": 1.0,
    "f1-score": 1.0,
    "support": 11,
    "confused_with": {}
  },
  "ask_exercise": {
    "precision": 1.0,
    "recall": 1.0,
    "f1-score": 1.0,
    "support": 10,
    "confused_with": {}
  },
  "ask_ergonomic_tips": {
    "precision": 1.0,
    "recall": 1.0,
    "f1-score": 1.0,
    "support": 15,
    "confused_with": {}
  },
  "ask_diet_tips": {
    "precision": 1.0,
    "recall": 1.0,
    "f1-score": 1.0,
    "support": 8,
    "confused_with": {}
  },
  "ask_time_management": {
    "precision": 1.0,
    "recall": 1.0,
    "f1-score": 1.0,
    "support": 10,
    "confused_with": {}
  },
  "ask_desk_dips_exercise": {
    "precision": 1.0,
    "recall": 1.0,
    "f1-score": 1.0,
    "support": 7,
    "confused_with": {}
  },
  "ask_twist_exercise": {
    "precision": 1.0,
    "recall": 1.0,
    "f1-score": 1.0,
    "support": 7,
    "confused_with": {}
  },
  "ask_desk_setup": {
    "precision": 1.0,
    "recall": 1.0,
    "f1-score": 1.0,
    "support": 11,
    "confused_with": {}
  },
  "ask_spine_stretches": {
    "precision": 1.0,
    "recall": 1.0,
    "f1-score": 1.0,
    "support": 13,
    "confused_with": {}
  },
  "ask_mindfulness": {
    "precision": 1.0,
    "recall": 1.0,
    "f1-score": 1.0,
    "support": 10,
    "confused_with": {}
  },
  "ask_stress_management": {
    "precision": 1.0,
    "recall": 1.0,
    "f1-score": 1.0,
    "support": 13,
    "confused_with": {}
  },
  "ask_seated_back_twists_exercise": {
    "precision": 1.0,
    "recall": 1.0,
    "f1-score": 1.0,
    "support": 8,
    "confused_with": {}
  },
  "ask_monitor_placement": {
    "precision": 1.0,
    "recall": 1.0,
    "f1-score": 1.0,
    "support": 13,
    "confused_with": {}
  },
  "mood_unhappy": {
    "precision": 1.0,
    "recall": 1.0,
    "f1-score": 1.0,
    "support": 14,
    "confused_with": {}
  },
  "ask_additional_exercise": {
    "precision": 1.0,
    "recall": 1.0,
    "f1-score": 1.0,
    "support": 6,
    "confused_with": {}
  },
  "bot_challenge": {
    "precision": 1.0,
    "recall": 1.0,
    "f1-score": 1.0,
    "support": 4,
    "confused_with": {}
  },
  "ask_hydration_tips": {
    "precision": 1.0,
    "recall": 1.0,
    "f1-score": 1.0,
    "support": 9,
    "confused_with": {}
  },
  "mood_great": {
    "precision": 1.0,
    "recall": 1.0,
    "f1-score": 1.0,
    "support": 14,
    "confused_with": {}
  },
  "ask_eye_strain_prevention": {
    "precision": 1.0,
    "recall": 1.0,
    "f1-score": 1.0,
    "support": 11,
    "confused_with": {}
  },
  "ask_keyboard_mouse_position": {
    "precision": 1.0,
    "recall": 1.0,
    "f1-score": 1.0,
    "support": 10,
    "confused_with": {}
  },
  "ask_seated_shoulder_shrugs_exercise": {
    "precision": 1.0,
    "recall": 1.0,
    "f1-score": 1.0,
    "support": 9,
    "confused_with": {}
  },
  "ask_leg_exercise": {
    "precision": 1.0,
    "recall": 1.0,
    "f1-score": 1.0,
    "support": 9,
    "confused_with": {}
  },
  "ask_hamstring_stretches": {
    "precision": 1.0,
    "recall": 1.0,
    "f1-score": 1.0,
    "support": 9,
    "confused_with": {}
  },
  "ask_calf_stretches": {
    "precision": 1.0,
    "recall": 1.0,
    "f1-score": 1.0,
    "support": 9,
    "confused_with": {}
  },
  "ask_shoulder_exercise": {
    "precision": 1.0,
    "recall": 1.0,
    "f1-score": 1.0,
    "support": 8,
    "confused_with": {}
  },
  "ask_work_life_balance": {
    "precision": 1.0,
    "recall": 1.0,
    "f1-score": 1.0,
    "support": 10,
    "confused_with": {}
  },
  "ask_stretch_exercise": {
    "precision": 1.0,
    "recall": 1.0,
    "f1-score": 1.0,
    "support": 11,
    "confused_with": {}
  },
  "ask_healthy_snacks": {
    "precision": 1.0,
    "recall": 1.0,
    "f1-score": 1.0,
    "support": 9,
    "confused_with": {}
  },
  "ask_portion_control": {
    "precision": 1.0,
    "recall": 1.0,
    "f1-score": 1.0,
    "support": 9,
    "confused_with": {}
  },
  "ask_calf_raises_exercise": {
    "precision": 1.0,
    "recall": 1.0,
    "f1-score": 1.0,
    "support": 8,
    "confused_with": {}
  },
  "ask_wrist_forearm_stretches": {
    "precision": 1.0,
    "recall": 1.0,
    "f1-score": 1.0,
    "support": 7,
    "confused_with": {}
  },
  "accuracy": 1.0,
  "macro avg": {
    "precision": 1.0,
    "recall": 1.0,
    "f1-score": 1.0,
    "support": 456
  },
  "weighted avg": {
    "precision": 1.0,
    "recall": 1.0,
    "f1-score": 1.0,
    "support": 456
  },
  "micro avg": {
    "precision": 1.0,
    "recall": 1.0,
    "f1-score": 1.0,
    "support": 456
  }
}